zwift_parser/__init__.py
zwift_parser/zwift_intervals.py
zwift_parser/zwift_parser.py
zwift_parser/zwift_workout.py
zwift_workouts_parser-1.0.1.dist-info/LICENSE
zwift_workouts_parser-1.0.1.dist-info/METADATA
zwift_workouts_parser-1.0.1.dist-info/WHEEL
zwift_workouts_parser-1.0.1.dist-info/top_level.txt
zwift_workouts_parser-1.0.1.dist-info/RECORD
