Metadata-Version: 2.1
Name: zwift-workouts-parser
Version: 1.0.1
Summary: A package that allows you to download workouts from https://whatsonzwift.com
Home-page: https://github.com/alexshpunt/zwift_workouts_parser
Author: Alexander Shpuntenko
Author-email: shpuntenko.a@gmail.com
Project-URL: Bug Tracker, https://github.com/alexshpunt/zwift_workouts_parser/issues
Classifier: Programming Language :: Python :: 3
Classifier: License :: OSI Approved :: MIT License
Classifier: Operating System :: OS Independent
Requires-Python: >=3.6
License-File: LICENSE
Requires-Dist: beautifulsoup4
Requires-Dist: certifi
Requires-Dist: lxml
